cli_dev_toolbox/ __init__.py
cli_dev_toolbox/converters.py
cli_dev_toolbox/fetcher.py
cli_dev_toolbox/toolbox.py
cli_dev_toolbox-0.1.2.dist-info/licenses/LICENSE
cli_dev_toolbox-0.1.2.dist-info/METADATA
cli_dev_toolbox-0.1.2.dist-info/WHEEL
cli_dev_toolbox-0.1.2.dist-info/entry_points.txt
cli_dev_toolbox-0.1.2.dist-info/top_level.txt
cli_dev_toolbox-0.1.2.dist-info/RECORD
