Metadata-Version: 2.4
Name: cli-dev-toolbox
Version: 0.1.2
Summary: A Python CLI utility for developers - JSON↔CSV conversion, pretty JSON, and URL fetch timing.
Author-email: Rahul Kumar <pkrk14@gmail.com>
License: MIT
Project-URL: Homepage, https://github.com/rahulkumar/cli-dev-toolbox
Project-URL: Documentation, https://github.com/rahulkumar/cli-dev-toolbox#readme
Project-URL: Repository, https://github.com/rahulkumar/cli-dev-toolbox
Project-URL: Issues, https://github.com/rahulkumar/cli-dev-toolbox/issues
Project-URL: Changelog, https://github.com/rahulkumar/cli-dev-toolbox/blob/main/CHANGELOG.md
Keywords: CLI,developer-tools,json,csv,http,python,data-conversion
Classifier: Development Status :: 3 - Alpha
Classifier: Intended Audience :: Developers
Classifier: License :: OSI Approved :: MIT License
Classifier: Operating System :: OS Independent
Classifier: Programming Language :: Python :: 3
Classifier: Programming Language :: Python :: 3.10
Classifier: Programming Language :: Python :: 3.11
Classifier: Programming Language :: Python :: 3.12
Classifier: Topic :: Software Development :: Libraries :: Python Modules
Classifier: Topic :: Utilities
Requires-Python: >=3.10
License-File: LICENSE
Requires-Dist: requests>=2.31.0
Provides-Extra: dev
Requires-Dist: pytest>=7.4.0; extra == "dev"
Requires-Dist: pytest-cov>=4.1.0; extra == "dev"
Requires-Dist: black>=23.0.0; extra == "dev"
Requires-Dist: flake8>=6.0.0; extra == "dev"
Requires-Dist: mypy>=1.5.0; extra == "dev"
Requires-Dist: types-requests>=2.31.0; extra == "dev"
Requires-Dist: twine>=4.0.0; extra == "dev"
Requires-Dist: build>=1.0.0; extra == "dev"
Requires-Dist: pre-commit>=3.3.0; extra == "dev"
Dynamic: license-file
